{
    "dayOfWeek": "Пт",
    "typeOfWeek": "Чет",
    "date": "2022-11-04",
    "subjects": [
        null,
        null,
        null,
        {
            "title": "Элективные курсы по физической культуре и спорту. Элективные курсы проходят в спортивном комплексе \"МИРАС\"",
            "shortTitle": "Физра",
            "type": "Практика",
            "prepod": "",
            "cabinet": "",
            "date": "1 сен - 1 янв"
        },
        null,
        {
            "title": "Теория вероятностей и математическая статистика",
            "shortTitle": "ТВИМС",
            "type": "Практика",
            "prepod": "Хайруллин М.Х.",
            "cabinet": "Д-104а",
            "date": "31 окт - 1 янв"
        },
        null,
        null
    ]
}